<?xml version="1.0" encoding="UTF-8"?>
<package packagerversion="1.9.1" version="2.0" xmlns="http://pear.php.net/dtd/package-2.0" xmlns:tasks="http://pear.php.net/dtd/tasks-1.0" xmlns:xsi="http://www.w3.org/2001/XMLSchema-instance" xsi:schemaLocation="http://pear.php.net/dtd/tasks-1.0     http://pear.php.net/dtd/tasks-1.0.xsd     http://pear.php.net/dtd/package-2.0     http://pear.php.net/dtd/package-2.0.xsd">
 <name>Yarrow</name>
 <channel>yo.yarrowdoc.org</channel>
 <summary>Simple documentation generator.</summary>
 <description>Winning the battle against entropy.</description>
 <lead>
  <name>Mark Rickerby</name>
  <user>maetl</user>
  <email>me@maetl.net</email>
  <active>yes</active>
 </lead>
 <date>2011-04-24</date>
 <time>19:52:01</time>
 <version>
  <release>0.0.3</release>
  <api>0.0.3</api>
 </version>
 <stability>
  <release>alpha</release>
  <api>alpha</api>
 </stability>
 <license uri="http://www.opensource.org/licenses/mit-license.php">MIT</license>
 <notes>
-
 </notes>
 <contents>
  <dir name="/">
   <file md5sum="984e153cacad4064fd8c5013a75d83f2" name="Yarrow/Analyzer.php" role="php">
    <tasks:replace from="{{version}}" to="version" type="package-info" />
   </file>
   <file md5sum="ee882d8b06b3b2a93a78643d503ffc32" name="Yarrow/Autoload.php" role="php">
    <tasks:replace from="{{version}}" to="version" type="package-info" />
   </file>
   <file md5sum="e231af5cd0c68eca7a2c154e60c0181a" name="Yarrow/ClassModel.php" role="php">
    <tasks:replace from="{{version}}" to="version" type="package-info" />
   </file>
   <file md5sum="c71aff78d53878e19d7ead516235a591" name="Yarrow/CodeListener.php" role="php">
    <tasks:replace from="{{version}}" to="version" type="package-info" />
   </file>
   <file md5sum="299e87a141d39078a2f1f7350d0ef59c" name="Yarrow/CodeParser.php" role="php">
    <tasks:replace from="{{version}}" to="version" type="package-info" />
   </file>
   <file md5sum="558b01ca787190628d5c94356158ec2a" name="Yarrow/ConfigurationError.php" role="php">
    <tasks:replace from="{{version}}" to="version" type="package-info" />
   </file>
   <file md5sum="0e64aaf71207a655a93800ac6366ca54" name="Yarrow/ConsoleRunner.php" role="php">
    <tasks:replace from="{{version}}" to="version" type="package-info" />
    <tasks:replace from="{{appname}}" to="name" type="package-info" />
   </file>
   <file md5sum="955409fd5e32f78790249f01fe48bbbb" name="Yarrow/DocblockModel.php" role="php">
    <tasks:replace from="{{version}}" to="version" type="package-info" />
   </file>
   <file md5sum="170178d5652e3b60822b0ebb9a1b287f" name="Yarrow/DocblockParser.php" role="php">
    <tasks:replace from="{{version}}" to="version" type="package-info" />
   </file>
   <file md5sum="35cc9df1ac2c2ef9fce49512cd20a39a" name="Yarrow/FileCollector.php" role="php">
    <tasks:replace from="{{version}}" to="version" type="package-info" />
   </file>
   <file md5sum="b43970e29998edf7c6f39d6e2d21aa2d" name="Yarrow/FileModel.php" role="php">
    <tasks:replace from="{{version}}" to="version" type="package-info" />
   </file>
   <file md5sum="bbcdf6b5be0b589b093a9645c391f82f" name="Yarrow/FunctionModel.php" role="php">
    <tasks:replace from="{{version}}" to="version" type="package-info" />
   </file>
   <file md5sum="e80fbe5d0387f308565238a74eeb83ea" name="Yarrow/Generator.php" role="php">
    <tasks:replace from="{{version}}" to="version" type="package-info" />
   </file>
   <file md5sum="0484a7fb200c554771b445d90899d280" name="Yarrow/ObjectModel.php" role="php">
    <tasks:replace from="{{version}}" to="version" type="package-info" />
   </file>
   <file md5sum="3404db87e61f6e31145c57a9f4af646c" name="Yarrow/PHPConverter.php" role="php">
    <tasks:replace from="{{version}}" to="version" type="package-info" />
   </file>
   <file md5sum="9c3ab556843fc268eb67fc5a925d1372" name="Yarrow/ScopeStack.php" role="php">
    <tasks:replace from="{{version}}" to="version" type="package-info" />
   </file>
   <file md5sum="fe811290e8ecc52ee896288500956151" name="Yarrow/TemplateConverter.php" role="php">
    <tasks:replace from="{{version}}" to="version" type="package-info" />
   </file>
   <file md5sum="e0b0707221e9b01e5ad4af3067cd8e1f" name="README" role="doc" />
   <file md5sum="36366f06dbee9ad7fbe669336aba8b25" name="LICENSE" role="doc" />
   <file md5sum="6dfffb47843d168ad670baf3e6bc8999" name="INTERNALS" role="doc" />
   <file baseinstalldir="/" install-as="yarrow" md5sum="028694af4fd5fa082deb828bcb49953a" name="yarrow.php" role="script">
    <tasks:replace from="{{version}}" to="version" type="package-info" />
   </file>
  </dir>
 </contents>
 <dependencies>
  <required>
   <php>
    <min>5.2.4</min>
   </php>
   <pearinstaller>
    <min>1.4.0</min>
   </pearinstaller>
  </required>
 </dependencies>
 <phprelease />
</package>
